{
  "legislative_session": "2025-2026",
  "identifier": "SF 4937",
  "title": "Identification of a lifetime permit to discharge a firearm or bow and arrow from a stationary motor vehicle provision on drivers' licenses and Minnesota identification cards",
  "from_organization": "~{\"classification\": \"upper\"}",
  "classification": [
    "bill"
  ],
  "subject": [
    "Hunting and Game",
    "Public Safety and Public Safety Department",
    "Transportation and Transportation Department"
  ],
  "abstracts": [],
  "other_titles": [],
  "other_identifiers": [
    {
      "identifier": "ocd-bill-mn-2025_2026-sf4937"
    }
  ],
  "actions": [
    {
      "description": "Introduction and first reading",
      "date": "2026-04-07",
      "organization_id": "~{\"classification\": \"upper\"}",
      "classification": [
        "introduction"
      ],
      "related_entities": [],
      "_processing": {
        "log_file_created": "2026-07-15T13:26:00Z"
      }
    },
    {
      "description": "Referred to Transportation",
      "date": "2026-04-07",
      "organization_id": "~{\"classification\": \"upper\"}",
      "classification": [
        "referral-committee"
      ],
      "related_entities": [],
      "_processing": {
        "log_file_created": "2026-07-15T13:26:00Z"
      }
    },
    {
      "description": "Author added Howe",
      "date": "2026-04-15",
      "organization_id": "~{\"classification\": \"upper\"}",
      "classification": [],
      "related_entities": [],
      "_processing": {
        "log_file_created": "2026-07-15T13:26:00Z"
      }
    }
  ],
  "sponsorships": [
    {
      "name": "Dahms",
      "classification": "primary",
      "entity_type": "person",
      "primary": true,
      "person_id": "~{\"name\": \"Dahms\"}",
      "organization_id": null
    },
    {
      "name": "Howe",
      "classification": "cosponsor",
      "entity_type": "person",
      "primary": false,
      "person_id": "~{\"name\": \"Howe\"}",
      "organization_id": null
    }
  ],
  "related_bills": [
    {
      "identifier": "HF 4670",
      "legislative_session": "2025-2026",
      "relation_type": "companion"
    }
  ],
  "versions": [
    {
      "note": "Introduction",
      "links": [
        {
          "url": "https://www.revisor.mn.gov/bills/94/2026/0/SF/4937/versions/0/",
          "media_type": "text/html"
        }
      ],
      "date": "2026-03-26",
      "classification": ""
    }
  ],
  "documents": [],
  "citations": [],
  "sources": [
    {
      "url": "https://www.revisor.mn.gov/bills/94/2026/0/SF/4937?list=open&body=Senate",
      "note": ""
    }
  ],
  "extras": {},
  "jurisdiction": {
    "id": "ocd-jurisdiction/country:us/state:mn/government",
    "name": "Minnesota",
    "classification": "state",
    "division_id": "ocd-division/country:us/state:mn"
  },
  "_processing": {
    "logs_latest_update": "2026-07-15T13:26:00Z"
  }
}