{
  "legislative_session": "2025-2026",
  "identifier": "HF 4973",
  "title": "Minnesota Main Streets special license plates established, and money appropriated.",
  "from_organization": "~{\"classification\": \"lower\"}",
  "classification": [
    "bill"
  ],
  "subject": [
    "Appropriations",
    "Motor Vehicles",
    "Transportation and Transportation Department"
  ],
  "abstracts": [],
  "other_titles": [],
  "other_identifiers": [
    {
      "identifier": "ocd-bill-mn-2025_2026-hf4973"
    }
  ],
  "actions": [
    {
      "description": "Introduction and first reading, referred to Transportation Finance and Policy",
      "date": "2026-04-16",
      "organization_id": "~{\"classification\": \"lower\"}",
      "classification": [
        "introduction",
        "referral-committee"
      ],
      "related_entities": [],
      "_processing": {
        "log_file_created": "2026-07-15T13:25:59Z"
      }
    },
    {
      "description": "Author added Pursell",
      "date": "2026-05-16",
      "organization_id": "~{\"classification\": \"lower\"}",
      "classification": [],
      "related_entities": [],
      "_processing": {
        "log_file_created": "2026-07-15T13:25:59Z"
      }
    }
  ],
  "sponsorships": [
    {
      "name": "Luger-Nikolai",
      "classification": "primary",
      "entity_type": "person",
      "primary": true,
      "person_id": "~{\"name\": \"Luger-Nikolai\"}",
      "organization_id": null
    },
    {
      "name": "Pursell",
      "classification": "cosponsor",
      "entity_type": "person",
      "primary": false,
      "person_id": "~{\"name\": \"Pursell\"}",
      "organization_id": null
    }
  ],
  "related_bills": [
    {
      "identifier": "SF 4405",
      "legislative_session": "2025-2026",
      "relation_type": "companion"
    }
  ],
  "versions": [
    {
      "note": "Introduction",
      "links": [
        {
          "url": "https://www.revisor.mn.gov/bills/94/2026/0/HF/4973/versions/0/",
          "media_type": "text/html"
        }
      ],
      "date": "2026-04-14",
      "classification": ""
    }
  ],
  "documents": [],
  "citations": [],
  "sources": [
    {
      "url": "https://www.revisor.mn.gov/bills/94/2026/0/HF/4973?list=open&body=House",
      "note": ""
    }
  ],
  "extras": {},
  "jurisdiction": {
    "id": "ocd-jurisdiction/country:us/state:mn/government",
    "name": "Minnesota",
    "classification": "state",
    "division_id": "ocd-division/country:us/state:mn"
  },
  "_processing": {
    "logs_latest_update": "2026-07-15T13:25:59Z",
    "text_extraction_latest_update": "2026-07-15T16:44:27.849681Z"
  }
}